noisydatacleaner/__init__.py
noisydatacleaner/_labelcorrector.py
noisydatacleaner/_noiseremover.py
noisydatacleaner-1.0.5.dist-info/LICENSE
noisydatacleaner-1.0.5.dist-info/METADATA
noisydatacleaner-1.0.5.dist-info/WHEEL
noisydatacleaner-1.0.5.dist-info/top_level.txt
noisydatacleaner-1.0.5.dist-info/RECORD
