Metadata-Version: 2.1
Name: noisydatacleaner
Version: 1.0.5
Summary: Noise Detection and Label Correcting Package
Home-page: https://github.com/jaotheboss/NoisyDataCleaner
Author: Teo Jao Ming
Author-email: jaomingteo@gmail.com
License: UNKNOWN
Project-URL: Bug Tracker, https://github.com/jaotheboss/NoisyDataCleaner/issues
Platform: UNKNOWN
Classifier: Programming Language :: Python :: 3.8
Classifier: License :: OSI Approved :: MIT License
Classifier: Operating System :: OS Independent
Requires-Python: >=3.8
Requires-Dist: scikit-learn
Requires-Dist: numpy
Requires-Dist: pandas
